dgsettings/__init__.py
dgsettings/db_storage.py
dgsettings/errors.py
dgsettings/file_storage.py
dgsettings/redis_storage.py
dgsettings/settings.py
dgsettings/storage.py
dgsettings-1.0.0a10.dist-info/licenses/LICENSE
dgsettings-1.0.0a10.dist-info/METADATA
dgsettings-1.0.0a10.dist-info/WHEEL
dgsettings-1.0.0a10.dist-info/top_level.txt
dgsettings-1.0.0a10.dist-info/RECORD
