Metadata-Version: 2.4
Name: dgsettings
Version: 1.0.0a10
Summary: Simple settings manager
Author-email: Roman Rasputin <admin@roro.su>
License: MIT License
Project-URL: Homepage, https://gitlab.com/gng-group/dgsettings
Project-URL: BugTracker, https://gitlab.com/gng-group/dgsettings/issues
Keywords: settings,config
Classifier: Development Status :: 4 - Beta
Classifier: Intended Audience :: Developers
Classifier: License :: OSI Approved :: MIT License
Classifier: Programming Language :: Python :: 3
Classifier: Programming Language :: Python :: 3.10
Classifier: Programming Language :: Python :: 3.11
Classifier: Programming Language :: Python :: 3.12
Classifier: Programming Language :: Python :: 3.13
Classifier: Operating System :: OS Independent
Classifier: Topic :: Software Development :: Libraries :: Python Modules
Classifier: Topic :: System :: Logging
Requires-Python: >=3.10
License-File: LICENSE
Requires-Dist: pyyaml>=5.1
Requires-Dist: dotenv
Provides-Extra: db
Requires-Dist: sqlalchemy; extra == "db"
Requires-Dist: psycopg2-binary; extra == "db"
Provides-Extra: redis
Requires-Dist: redis>=6.2.0; extra == "redis"
Provides-Extra: all
Requires-Dist: sqlalchemy; extra == "all"
Requires-Dist: psycopg2-binary; extra == "all"
Requires-Dist: redis>=6.2.0; extra == "all"
Dynamic: license-file
